device.py
who.py
who_is_on_my_wifi.py
who_is_on_my_wifi-1.3.5.data/scripts/device.py
who_is_on_my_wifi-1.3.5.data/scripts/who.py
who_is_on_my_wifi-1.3.5.data/scripts/who_is_on_my_wifi.py
who_is_on_my_wifi-1.3.5.dist-info/LICENSE.txt
who_is_on_my_wifi-1.3.5.dist-info/METADATA
who_is_on_my_wifi-1.3.5.dist-info/WHEEL
who_is_on_my_wifi-1.3.5.dist-info/entry_points.txt
who_is_on_my_wifi-1.3.5.dist-info/top_level.txt
who_is_on_my_wifi-1.3.5.dist-info/RECORD
