Metadata-Version: 2.1
Name: who-is-on-my-wifi
Version: 1.3.5
Summary: Help you to find who is stealing your WiFI network, scan your WiFI and show you how many devices are currently connected!
Home-page: https://github.com/tucnakomet1/Python-Who-Is-On-My-WiFi
Author: Karel Velicka
Author-email: tucnakomet@gmail.com
License: MIT
Platform: any
Classifier: Environment :: Console
Classifier: Programming Language :: Python :: 3
Classifier: Programming Language :: Python :: 3.6
Classifier: Programming Language :: Python :: 3.8
Classifier: Programming Language :: Python :: 3.9
Classifier: License :: OSI Approved :: MIT License
Classifier: Operating System :: POSIX
Classifier: Operating System :: Unix
Classifier: Operating System :: Microsoft :: Windows
Classifier: Operating System :: OS Independent
Requires-Dist: getmac
Requires-Dist: scapy
